CHANGES.txt
MANIFEST.in
README.rst
setup.py
isotoma/__init__.py
isotoma.recipe.template.egg-info/PKG-INFO
isotoma.recipe.template.egg-info/SOURCES.txt
isotoma.recipe.template.egg-info/dependency_links.txt
isotoma.recipe.template.egg-info/entry_points.txt
isotoma.recipe.template.egg-info/namespace_packages.txt
isotoma.recipe.template.egg-info/not-zip-safe
isotoma.recipe.template.egg-info/requires.txt
isotoma.recipe.template.egg-info/top_level.txt
isotoma/recipe/__init__.py
isotoma/recipe/template/__init__.py