Metadata-Version: 1.0
Name: isotoma.recipe.template
Version: 0.0.4
Summary: Wrapper around Cheetah + JSON to provide simple buildout templating
Home-page: UNKNOWN
Author: John Carr
Author-email: john.carr@isotoma.com
License: Apache Software License
Keywords: buildout template
Platform: UNKNOWN
Classifier: Framework :: Buildout
Classifier: Intended Audience :: System Administrators
Classifier: Operating System :: POSIX
Classifier: License :: OSI Approved :: Apache Software License
